nutrition_pad/__init__.py
nutrition_pad/amounts.py
nutrition_pad/calories.py
nutrition_pad/client_cli.py
nutrition_pad/data.py
nutrition_pad/entries_cli.py
nutrition_pad/food_cli.py
nutrition_pad/main.py
nutrition_pad/notes.py
nutrition_pad/notes_cli.py
nutrition_pad/polling.py
nutrition_pad/record_cli.py
nutrition_pad/styles.py
nutrition_pad/unknown_cli.py
nutrition_pad-4.2.1.dist-info/METADATA
nutrition_pad-4.2.1.dist-info/WHEEL
nutrition_pad-4.2.1.dist-info/entry_points.txt
nutrition_pad-4.2.1.dist-info/top_level.txt
nutrition_pad-4.2.1.dist-info/RECORD
