Metadata-Version: 2.4
Name: nutrition-pad
Version: 4.2.1
Summary: Nutrition tracking with tablet-friendly interface
Requires-Python: >=3.8
Requires-Dist: flask>=2.0.0
Requires-Dist: toml>=0.10.2
Requires-Dist: requests>=2.20.0
